LICENSE
README.md
setup.cfg
setup.py
bones/core/context.py
bones/core/errors.py
bones/core/sentinels.py
bones/core/utils.py
bones/kernel/base.py
bones/lang/types.py
bones/ts/core.py
bones/ts/metatypes.py
bones/ts/select.py
bones/ts/type_lang.py
bones/ts/_type_lang/TypeLangLexer.py
bones/ts/_type_lang/TypeLangListener.py
bones/ts/_type_lang/TypeLangParser.py
bones/ts/_type_lang/ast_builder.py
bones/ts/_type_lang/ast_nodes.py
bones/ts/_type_lang/fits.py
bones/ts/_type_lang/jones_type_manager.py
bones/ts/_type_lang/py_type_manager.py
bones/ts/_type_lang/syntax_checker.py
bones/ts/_type_lang/utils.py
coppertop/_scopes.py
coppertop/pipe.py
coppertop_bones.egg-info/PKG-INFO
coppertop_bones.egg-info/SOURCES.txt
coppertop_bones.egg-info/dependency_links.txt
coppertop_bones.egg-info/not-zip-safe
coppertop_bones.egg-info/requires.txt
coppertop_bones.egg-info/top_level.txt